appinstall/__init__.py
appinstall/call_service_api.py
Common_Appinstall-1.0.0.3.dist-info/METADATA
Common_Appinstall-1.0.0.3.dist-info/WHEEL
Common_Appinstall-1.0.0.3.dist-info/top_level.txt
Common_Appinstall-1.0.0.3.dist-info/RECORD
