Metadata-Version: 2.1
Name: Common-Appinstall
Version: 1.0.0.3
Summary: Common Appinstall Package
Home-page: https://www.nhndata.com
Author: juhyun
Author-email: jhcheon@nhn.com
License: MIT
Platform: UNKNOWN
Requires-Python: >=3
